mgdl/__init__.py
mgdl/cli_entry.py
mgdl-1.1.dist-info/LICENSE
mgdl-1.1.dist-info/METADATA
mgdl-1.1.dist-info/WHEEL
mgdl-1.1.dist-info/entry_points.txt
mgdl-1.1.dist-info/top_level.txt
mgdl-1.1.dist-info/RECORD
