Metadata-Version: 2.1
Name: mgdl
Version: 1.1
Summary: CLI Manga Downloader
Home-page: https://github.com/FR0ST1N/mgdl
Author: FR0ST1N
Author-email: iamfrostin@gmail.com
License: MIT
Keywords: cli anime manga downloader
Platform: UNKNOWN
Classifier: Development Status :: 5 - Production/Stable
Classifier: Environment :: Console
Classifier: Intended Audience :: End Users/Desktop
Classifier: Intended Audience :: Developers
Classifier: License :: OSI Approved :: MIT License
Classifier: Operating System :: OS Independent
Classifier: Programming Language :: Python :: 3
Requires-Dist: beautifulsoup4
Requires-Dist: pyprind
